jclib/__init__.py
jclib/actions.py
jclib-0.0.1.dist-info/DESCRIPTION.rst
jclib-0.0.1.dist-info/METADATA
jclib-0.0.1.dist-info/RECORD
jclib-0.0.1.dist-info/WHEEL
jclib-0.0.1.dist-info/metadata.json
jclib-0.0.1.dist-info/top_level.txt
